Workbook

Sheet Pointers
A1: For trracking the Revenue Realization, Resource Burn Rate and Gross Margins
A3: Revenue Realization | B3: How much of the expected/billed revenue is actually realised | C3: Actual Revenue by Planned Revenue
A4: Resource Burn Rate | B4: To be measured in Cost | C4: Burn Rate = Total Resource Cost/Time Period
A5: Monthly Burn | B5: Resource Cost by Number of Months
A6: for Efficiency | B6: Revenue/Resource Count
A7: Gross Margin | B7: (Revenue-Cost) by Revenue
A9: Net Burn | B9: Cost-Revenue

Sheet Data Sheet
A1: Roles | C1: Emp/Contractor | E1: Skill
A2: Google Delivery Lead | C2: Employee | E2: Dev
A3: Integration Lead | C3: Contractor | E3: QA
A4: Google Tech Lead | E4: UAT
A5: Project Manager | E5: Deployment
A6: Business Analyst
A7: CX Design Lead
A8: CX Designer
A9: Google Developer
A10: QA
A11: BI Dashboard Lead
A12: BI Dashboard UI Developer
A13: ETL Developer
A14: Genesys Developer
A15: UI / UX Developer
A16: Fullstack Developer
A17: QA Lead
... A26: Product Owner

Sheet Resource Allocation
A1: Project Name | B1: Employee Code | C1: Employee Name | D1: Emp/Contractor | E1: Skill | F1: Role | G1: Fortnight | H1: Allocated Hrs | I1: Actual Hrs | J1: Cost per Hr | K1: Actual Cost
A2: Auto Case - Auto | D2: Employee | E2: Dev | F2: Project Manager | G2: F1 | H2: 160 | I2: 180 | J2: 100 | K2: =I2*J2 -> 18000
A3: Auto Case - Auto | F3: Integration Lead | G3: F1 | H3: 200 | I3: 220 | J3: 50 | K3: =I3*J3 -> 11000
A4: Auto Case - Auto | F4: Business Analyst | G4: F2 | H4: 150 | I4: 200 | J4: 30 | K4: =I4*J4 -> 6000
A5: Auto Case - Pharma D | F5: Google Tech Lead | G5: F1 | H5: 110 | I5: 150 | J5: 80 | K5: =I5*J5 -> 12000
A6: Auto Case - Pharma D | F6: CX Design Lead | G6: F2 | H6: 80 | I6: 150 | J6: 100 | K6: =I6*J6 -> 15000

Sheet Project Summary
A1: Project Name | B1: Start Date | C1: End Date | D1: Total Revenue | E1: Total Cost | F1: Project Burn Rate | G1: Project GM | H1: Burn Status | I1: Cummulative Status (Project Burn + Gross Margim)
A2: Auto Case - Auto | B2: 45658 | C2: 46112 | D2: =SUMIFS('Project Wise Revenue'!E:E,'Project Wise Revenue'!B:B,'Project Summary'!A2) -> 200000 | E2: =SUMIFS('Resource Allocation'!K:K,'Resource Allocation'!A:A,'Project Summary'!A2) -> 35000 | F2: =E2/D2 -> 0.175 | G2: =(D2-E2)/D2 -> 0.825 | H2: =IF(G2<0,"Red",IF(G2<0.2,"Amber","Green")) -> Green | I2: =IF(OR(G2<0,F2>0.85),"Red",IF(G2>0.7,"Amber","Green")) -> Amber
A3: Auto Case - Pharma D | B3: 45672 | C3: 46127 | D3: =SUMIFS('Project Wise Revenue'!E:E,'Project Wise Revenue'!B:B,'Project Summary'!A3) -> 450000 | E3: =SUMIFS('Resource Allocation'!K:K,'Resource Allocation'!A:A,'Project Summary'!A3) -> 27000 | F3: =E3/D3 -> 0.06 | G3: =(D3-E3)/D3 -> 0.94 | H3: =IF(G3<0,"Red",IF(G3<0.2,"Amber","Green")) -> Green | I3: =IF(OR(G3<0,F3>0.85),"Red",IF(G3>0.7,"Amber","Green")) -> Amber

Sheet Project Wise Revenue
A1: Project Code | B1: Project Name | C1: Period (Month) | D1: Planned Revenue | E1: Actual Revenue
A2: HUM0001 | B2: Auto Case - Auto | C2: 46048 | D2: 500000 | E2: 200000
A3: HUM0002 | B3: Auto Case - Pharma D | C3: 46048 | D3: 800000 | E3: 450000

Sheet Project Timeline Burn 
A1: Project Name | B1: Period (Fortnight) | C1: Total Cost | D1: Actual Revenue | E1: Revenue Realised | F1: Burn Rate | G1: Gross Margin | H1: Burn Status
A2: Auto Case - Auto | B2: F1 | C2: =SUMIFS('Resource Allocation'!K:K,'Resource Allocation'!A:A,'Project Timeline Burn '!A2,'Resource Allocation'!G:G,'Project Timeline Burn '!B2) -> 29000 | D2: =SUMIFS('Project Wise Revenue'!E:E,'Project Wise Revenue'!B:B,'Project Timeline Burn '!A2,'Project Wise Revenue'!C:C,'Project Timeline Burn '!B2) -> 0 | E2: =D2/SUMIFS('Project Wise Revenue'!D:D,'Project Wise Revenue'!B:B,'Project Timeline Burn '!A2,'Project Wise Revenue'!C:C,'Project Timeline Burn '!B2) -> #DIV/0! | F2: =C2/D2 -> #DIV/0! | G2: =(D2-C2)/D2 -> #DIV/0! | H2: =IF(F2>0.85,"Red",IF(F2>0.6,"Amber","Green")) -> #DIV/0!
A3: Auto Case - Auto | B3: F2 | C3: =SUMIFS('Resource Allocation'!K:K,'Resource Allocation'!A:A,'Project Timeline Burn '!A3,'Resource Allocation'!G:G,'Project Timeline Burn '!B3) -> 6000 | D3: =SUMIFS('Project Wise Revenue'!E:E,'Project Wise Revenue'!B:B,'Project Timeline Burn '!A3,'Project Wise Revenue'!C:C,'Project Timeline Burn '!B3) -> 0 | E3: =D3/SUMIFS('Project Wise Revenue'!D:D,'Project Wise Revenue'!B:B,'Project Timeline Burn '!A3,'Project Wise Revenue'!C:C,'Project Timeline Burn '!B3) -> #DIV/0! | F3: =C3/D3 -> #DIV/0! | G3: =(D3-C3)/D3 -> #DIV/0! | H3: =IF(F3>0.85,"Red",IF(F3>0.75,"Amber","Green")) -> #DIV/0!
A4: Auto Case - Pharma D | B4: F1 | C4: =SUMIFS('Resource Allocation'!K:K,'Resource Allocation'!A:A,'Project Timeline Burn '!A4,'Resource Allocation'!G:G,'Project Timeline Burn '!B4) -> 12000 | D4: =SUMIFS('Project Wise Revenue'!E:E,'Project Wise Revenue'!B:B,'Project Timeline Burn '!A4,'Project Wise Revenue'!C:C,'Project Timeline Burn '!B4) -> 0 | E4: =D4/SUMIFS('Project Wise Revenue'!D:D,'Project Wise Revenue'!B:B,'Project Timeline Burn '!A4,'Project Wise Revenue'!C:C,'Project Timeline Burn '!B4) -> #DIV/0! | F4: =C4/D4 -> #DIV/0! | G4: =(D4-C4)/D4 -> #DIV/0! | H4: =IF(F4>0.85,"Red",IF(F4>0.75,"Amber","Green")) -> #DIV/0!
A5: Auto Case - Pharma D | B5: F2 | C5: =SUMIFS('Resource Allocation'!K:K,'Resource Allocation'!A:A,'Project Timeline Burn '!A5,'Resource Allocation'!G:G,'Project Timeline Burn '!B5) -> 15000 | D5: =SUMIFS('Project Wise Revenue'!E:E,'Project Wise Revenue'!B:B,'Project Timeline Burn '!A5,'Project Wise Revenue'!C:C,'Project Timeline Burn '!B5) -> 0 | E5: =D5/SUMIFS('Project Wise Revenue'!D:D,'Project Wise Revenue'!B:B,'Project Timeline Burn '!A5,'Project Wise Revenue'!C:C,'Project Timeline Burn '!B5) -> #DIV/0! | F5: =C5/D5 -> #DIV/0! | G5: =(D5-C5)/D5 -> #DIV/0! | H5: =IF(F5>0.85,"Red",IF(F5>0.75,"Amber","Green")) -> #DIV/0!

Sheet Data Fields
A1: Client Name | B1: Start Date | C1: End Date | D1: Project Code | E1: Description | F1: Project Revenue | G1: Capability | H1: SOW SF ref | I1: SOW Reveneue | J1: Gross margin

Sheet Sheet7
D3: Values | H3: Sum of Total Cost
A4: Project Code | B4: Jan-26 | C4: Project Name | D4: Count of Emp ID | E4: Sum of Total Cost | H4: Project Code | I4: Project Name | J4: Employee Name | K4: Jan-26 | L4: Total
A5: HUM0001 | B5: 0.25 | C5: Auto Case - Auto | D5: 1 | E5: 737.35611 | H5: HUM0001 | I5: Auto Case - Auto | J5: Aanchal Garg | K5: 1 | L5: 6303.4495
B6: 1 | C6: Auto Case - Auto | D6: 26 | E6: 458979.76 | J6: Abhishek Ganguly | K6: 0.25 | L6: 737.35611
A7: HUM0002 | B7: 1 | C7: Auto Case - Pharma D | D7: 18 | E7: 378413.29 | J7: Aishani Bhatnagar | K7: 1 | L7: 6303.4495
A8: Grand Total | D8: 45 | E8: 838130.4 | J8: Ajeesh Balakrishnan | K8: 1 | L8: 69467.772
J9: Amar Utkarsh | K9: 1 | L9: 11432.562
J10: Amit Jha | K10: 1 | L10: 21704.696
J11: Ananya Borah | K11: 1 | L11: 11432.562
J12: Anuj Dubey | K12: 1 | L12: 6303.4495
J13: Deepak Saini | K13: 1 | L13: 11432.562
J14: Harshil Andugulapati | K14: 1 | L14: 11432.562
J15: Mitali Tripathi | K15: 1 | L15: 21704.696
J16: Natalia Militsa | K16: 1 | L16: 69467.772
J17: Nihal Shaik | K17: 1 | L17: 11432.562
J18: Niketa . | K18: 1 | L18: 21704.696
J19: Nirmal Jose P | K19: 1 | L19: 11432.562
J20: Nivedita Dixit | K20: 1 | L20: 6303.4495
... J31: Vipasha . | K31: 1 | L31: 11432.562
I32: Auto Case - Auto Total | L32: 459717.12
H33: HUM0002 | I33: Auto Case - Pharma D | J33: Ankush Hora | K33: 1 | L33: 77674.758
J34: Anne Rodelene Pelario Tigol | K34: 1 | L34: 32585.552
J35: Divya Chaudhary | K35: 1 | L35: 21704.696
J36: Ishita Koradia | K36: 1 | L36: 6303.4495
J37: Koushik C S | K37: 1 | L37: 6303.4495
J38: Krishna . | K38: 1 | L38: 11432.562
J39: Madhurima Boral | K39: 1 | L39: 6303.4495
J40: Manudeep Yalavali | K40: 1 | L40: 21704.696
J41: Mayur Shingavi | K41: 1 | L41: 43909.806
J42: Rajeev Kumar | K42: 1 | L42: 11432.562
J43: Ravi Khurana | K43: 1 | L43: 21704.696
J44: Shalini Dey | K44: 1 | L44: 11432.562
J45: Soumyashree Dash | K45: 1 | L45: 48744.327
... J50: Yashkumar Amrutlal Kavaiya | K50: 1 | L50: 6303.4495
I51: Auto Case - Pharma D Total | L51: 378413.29
H52: Grand Total | L52: 838130.4

Sheet Project Master
A1: Project Code | B1: Project Name | C1: Start Date | D1: End Date | E1: Total Budget | F1: Currency | G1: Total Revenue
A2: HUM0001 | B2: Auto Case - Auto | C2: 45658 | D2: 31-03-2026 | E2: 10000000 | G2: 13000000
A3: HUM0002 | B3: Auto Case - Pharma D | C3: 45658 | D3: 31-03-2026 | E3: 7500000 | G3: 9500000

Sheet Resource Rate Card
A1: Roles | C1: Emp/Contractor | E1: Skill | H1: Sub Band | I1: Location | J1: Role | K1: Role as per Rate Card | L1: Monthly Rate Card | N1: RATE LIST Employee
A2: Google Delivery Lead | C2: Employee | E2: Dev | G2: =H2&I2 -> A2India | H2: A2 | I2: India | J2: QA | K2: =J2 -> QA | L2: 1474.7122 | N2: Band | O2: US | P2: UK | Q2: PHP | R2: India
A3: Integration Lead | C3: Contractor | E3: QA | G3: =H3&I3 -> B1India | H3: B1 | I3: India | J3: CX Designer | K3: =J3 -> CX Designer | L3: 3151.7248 | N3: A | O3: 0 | P3: 0 | Q3: 2332.939 | R3: 1474.7122
A4: Google Tech Lead | E4: UAT | G4: =H4&I4 -> B1US | H4: B1 | I4: US | J4: Google Developer | K4: =J4 -> Google Developer | L4: 15690.09 | N4: B | O4: 15690.09 | P4: 13812.943 | Q4: 3998.606 | R4: 3151.7248
A5: Project Manager | E5: Deployment | G5: =H5&I5 -> B2India | H5: B2 | I5: India | J5: Data Analyst | K5: =J5 -> Data Analyst | L5: 3151.7248 | N5: C | O5: 24372.163 | P5: 18759.509 | Q5: 9201.3542 | R5: 5716.2812
A6: Business Analyst | G6: =H6&I6 -> C1India | H6: C1 | I6: India | J6: BI Dashboard UI Developer | K6: =J6 -> BI Dashboard UI Developer | L6: 5716.2812 | N6: D | O6: 34733.886 | P6: 31563.528 | Q6: 16292.776 | R6: 10852.348
A7: CX Design Lead | G7: =H7&I7 -> C1US | H7: C1 | I7: US | J7: QA | K7: =J7 -> QA | L7: 24372.163 | N7: E | O7: 38837.379 | P7: 0 | Q7: 21954.903 | R7: 14237.976
A8: CX Designer | G8: =H8&I8 -> C2India | H8: C2 | I8: India | J8: Business Analyst | K8: =J8 -> Business Analyst | L8: 5716.2812
A9: Google Developer | G9: =H9&I9 -> D1India | H9: D1 | I9: India | J9: BI Dashboard Lead | K9: =J9 -> BI Dashboard Lead | L9: 10852.348
A10: QA | G10: =H10&I10 -> D1PHP | H10: D1 | I10: PHP | J10: Project Manager | K10: =J10 -> Project Manager | L10: 16292.776 | N10: RATE LIST Contractor
A11: BI Dashboard Lead | G11: =H11&I11 -> D1US | H11: D1 | I11: US | J11: CX Design Lead | K11: =J11 -> CX Design Lead | L11: 34733.886 | N11: Band | O11: India
A12: BI Dashboard UI Developer | G12: =H12&I12 -> D2India | H12: D2 | I12: India | J12: CI Optimization Lead | K12: =J12 -> CI Optimization Lead | L12: 10852.348 | N12: A | O12: 0
A13: ETL Developer | G13: =H13&I13 -> D2US | H13: D2 | I13: US | J13: Program Lead | K13: =J13 -> Program Lead | L13: 34733.886 | N13: B | O13: 0
A14: Genesys Developer | G14: =H14&I14 -> E1PHP | H14: E1 | I14: PHP | J14: Overall Program Lead | K14: =J14 -> Overall Program Lead | L14: 21954.903 | N14: C | O14: 0
A15: UI / UX Developer | G15: =H15&I15 -> E1US | H15: E1 | I15: US | J15: Engagement Lead | K15: =J15 -> Engagement Lead | L15: 38837.379 | N15: D | O15: 0
A16: Fullstack Developer | N16: E | O16: 0
A17: QA Lead
A18: Solution Architect | I18: Location | J18: Band
A19: CI Optimization Lead | I19: US | J19: A1
A20: Data Analyst | I20: UK | J20: A2
A21: Google Support Lead | I21: PHP | J21: B1
A22: Google Support | I22: India | J22: B2
A23: Program Lead | J23: C1
A24: SAFe Coach | J24: C2
A25: RTE | J25: D1
A26: Product Owner | J26: D2
J27: E1
J28: E2

Sheet Monthly Resource
A1: Project Code | B1: Project Name | C1: Month | D1: Emp. Code | E1: Emp. Name | F1: Role | G1: Emp/Contractor | H1: Band | I1: Working | J1: Location | K1: Allocation%
A2: HUM0001 | B2: Auto Case - Auto | C2: 46048 | D2: Abhishek191376 | E2: Abhishek Ganguly | F2: QA | G2: Employee | H2: A2 | I2: A | J2: India | K2: 25
A3: HUM0001 | B3: Auto Case - Auto | C3: 46048 | D3: Amit127844 | E3: Amit Jha | F3: 0 | G3: Employee | H3: D2 | I3: D | J3: India | K3: 100
A4: HUM0001 | B4: Auto Case - Auto | C4: 46048 | D4: Ananya193970 | E4: Ananya Borah | F4: CX Designer | G4: Employee | H4: C2 | I4: C | J4: India | K4: 50
A5: HUM0002 | B5: Auto Case - Pharma D | C5: 46048 | D5: 10125 | E5: Krishna . | F5: CX Designer | G5: Employee | H5: C1 | I5: C | J5: India | K5: 100
A6: HUM0002 | B6: Auto Case - Pharma D | C6: 46048 | D6: Madhurima217704 | E6: Madhurima Boral | F6: CX Designer | G6: Employee | H6: B1 | I6: B | J6: India | K6: 50
A7: HUM0001 | B7: Auto Case - Auto | C7: 46048 | D7: Piyush231958 | E7: Piyush Lahiry | F7: Google Tech Lead | G7: Employee | H7: C1 | I7: C | J7: India | K7: 75
A8: HUM0001 | B8: Auto Case - Auto | C8: 46048 | D8: Pragya262685 | E8: Pragya Sood | F8: QA Lead | G8: Employee | H8: C2 | I8: C | J8: India | K8: 10
A9: HUM0001 | B9: Auto Case - Auto | C9: 46048 | D9: Vipasha194680 | E9: Vipasha . | F9: Google Tech Lead | G9: Employee | H9: C1 | I9: C | J9: India | K9: 25

Sheet Monthly Resource Allocation
A1: TRIM | B1: Project Code | C1: Project Name | D1: Emp ID | E1: Employee Name | F1: Emp/Contractor | G1: Band | H1: Working | I1: Location | J1: Role | K1: Cost Per Month | L1: 46048 | M1: 46079 | N1: 46107 | O1: 46138 | P1: 46168 | Q1: 46199 | R1: 46229 | S1: 46260 | T1: 46291 | U1: 46321 | V1: 46352 | W1: 46382 | X1: Total Cost
A2: =J2&I2&G2 -> QAIndiaA2 | B2: HUM0001 | C2: Auto Case - Auto | D2: Abhishek191376 | E2: Abhishek Ganguly | F2: Employee | G2: A2 | H2: =LEFT(G2,1) -> A | I2: India | J2: QA | K2: =IF(F2="Contractor",VLOOKUP(H2,'Resource Rate Card'!$N$10:$O$16,2,0),IF(I2="India",VLOOKUP(H2,'Resource Rate Card'!$N$1:$R$7,5,0),IF(I2="PHP",VLOOKUP(H2,'Resource Rate Card'!$N$1:$R$7,4,0),IF(I2="UK",VLOOKUP(H2,'Resource Rate Card'!$N$1:$R$7,3,0),IF(I2="US",VLOOKUP(H2,'Resource Rate Card'!$N$1:$R$7,2,0)))))) -> 1474.7122 | L2: 0.25 | M2: 0.25 | N2: 0 | O2: 0 | P2: 0 | Q2: 0 | R2: 0 | S2: 0 | T2: 0 | U2: 0 | V2: 0 | W2: 0 | X2: =(K2*L2)+(K2*M2)+(K2*N2)+(K2*O2)+(K2*P2)+(K2*Q2)+(K2*R2)+(K2*S2)+(K2*T2)+(K2*U2)+(K2*V2)+(K2*W2) -> 737.35611
A3: =J3&I3&G3 -> 0IndiaD2 | B3: HUM0001 | C3: Auto Case - Auto | D3: Amit127844 | E3: Amit Jha | F3: Employee | G3: D2 | H3: =LEFT(G3,1) -> D | I3: India | J3: 0 | K3: =IF(F3="Contractor",VLOOKUP(H3,'Resource Rate Card'!$N$10:$O$16,2,0),IF(I3="India",VLOOKUP(H3,'Resource Rate Card'!$N$1:$R$7,5,0),IF(I3="PHP",VLOOKUP(H3,'Resource Rate Card'!$N$1:$R$7,4,0),IF(I3="UK",VLOOKUP(H3,'Resource Rate Card'!$N$1:$R$7,3,0),IF(I3="US",VLOOKUP(H3,'Resource Rate Card'!$N$1:$R$7,2,0)))))) -> 10852.348 | L3: 1 | M3: 1 | N3: 0 | O3: 0 | P3: 0 | Q3: 0 | R3: 0 | S3: 0 | T3: 0 | U3: 0 | V3: 0 | W3: 0 | X3: =(K3*L3)+(K3*M3)+(K3*N3)+(K3*O3)+(K3*P3)+(K3*Q3)+(K3*R3)+(K3*S3)+(K3*T3)+(K3*U3)+(K3*V3)+(K3*W3) -> 21704.696
A4: =J4&I4&G4 -> CX DesignerIndiaC2 | B4: HUM0001 | C4: Auto Case - Auto | D4: Ananya193970 | E4: Ananya Borah | F4: Employee | G4: C2 | H4: =LEFT(G4,1) -> C | I4: India | J4: CX Designer | K4: =IF(F4="Contractor",VLOOKUP(H4,'Resource Rate Card'!$N$10:$O$16,2,0),IF(I4="India",VLOOKUP(H4,'Resource Rate Card'!$N$1:$R$7,5,0),IF(I4="PHP",VLOOKUP(H4,'Resource Rate Card'!$N$1:$R$7,4,0),IF(I4="UK",VLOOKUP(H4,'Resource Rate Card'!$N$1:$R$7,3,0),IF(I4="US",VLOOKUP(H4,'Resource Rate Card'!$N$1:$R$7,2,0)))))) -> 5716.2812 | L4: 1 | M4: 1 | N4: 0 | O4: 0 | P4: 0 | Q4: 0 | R4: 0 | S4: 0 | T4: 0 | U4: 0 | V4: 0 | W4: 0 | X4: =(K4*L4)+(K4*M4)+(K4*N4)+(K4*O4)+(K4*P4)+(K4*Q4)+(K4*R4)+(K4*S4)+(K4*T4)+(K4*U4)+(K4*V4)+(K4*W4) -> 11432.562
A5: =J5&I5&G5 -> CX DesignerIndiaC1 | B5: HUM0002 | C5: Auto Case - Pharma D | D5: 10125 | E5: Krishna . | F5: Employee | G5: C1 | H5: =LEFT(G5,1) -> C | I5: India | J5: CX Designer | K5: =IF(F5="Contractor",VLOOKUP(H5,'Resource Rate Card'!$N$10:$O$16,2,0),IF(I5="India",VLOOKUP(H5,'Resource Rate Card'!$N$1:$R$7,5,0),IF(I5="PHP",VLOOKUP(H5,'Resource Rate Card'!$N$1:$R$7,4,0),IF(I5="UK",VLOOKUP(H5,'Resource Rate Card'!$N$1:$R$7,3,0),IF(I5="US",VLOOKUP(H5,'Resource Rate Card'!$N$1:$R$7,2,0)))))) -> 5716.2812 | L5: 1 | M5: 1 | N5: 0 | O5: 0 | P5: 0 | Q5: 0 | R5: 0 | S5: 0 | T5: 0 | U5: 0 | V5: 0 | W5: 0 | X5: =(K5*L5)+(K5*M5)+(K5*N5)+(K5*O5)+(K5*P5)+(K5*Q5)+(K5*R5)+(K5*S5)+(K5*T5)+(K5*U5)+(K5*V5)+(K5*W5) -> 11432.562
A6: =J6&I6&G6 -> CX DesignerIndiaB1 | B6: HUM0002 | C6: Auto Case - Pharma D | D6: Madhurima217704 | E6: Madhurima Boral | F6: Employee | G6: B1 | H6: =LEFT(G6,1) -> B | I6: India | J6: CX Designer | K6: =IF(F6="Contractor",VLOOKUP(H6,'Resource Rate Card'!$N$10:$O$16,2,0),IF(I6="India",VLOOKUP(H6,'Resource Rate Card'!$N$1:$R$7,5,0),IF(I6="PHP",VLOOKUP(H6,'Resource Rate Card'!$N$1:$R$7,4,0),IF(I6="UK",VLOOKUP(H6,'Resource Rate Card'!$N$1:$R$7,3,0),IF(I6="US",VLOOKUP(H6,'Resource Rate Card'!$N$1:$R$7,2,0)))))) -> 3151.7248 | L6: 1 | M6: 1 | N6: 0 | O6: 0 | P6: 0 | Q6: 0 | R6: 0 | S6: 0 | T6: 0 | U6: 0 | V6: 0 | W6: 0 | X6: =(K6*L6)+(K6*M6)+(K6*N6)+(K6*O6)+(K6*P6)+(K6*Q6)+(K6*R6)+(K6*S6)+(K6*T6)+(K6*U6)+(K6*V6)+(K6*W6) -> 6303.4495
A7: =J7&I7&G7 -> Google Tech LeadIndiaC1 | B7: HUM0001 | C7: Auto Case - Auto | D7: Piyush231958 | E7: Piyush Lahiry | F7: Employee | G7: C1 | H7: =LEFT(G7,1) -> C | I7: India | J7: Google Tech Lead | K7: =IF(F7="Contractor",VLOOKUP(H7,'Resource Rate Card'!$N$10:$O$16,2,0),IF(I7="India",VLOOKUP(H7,'Resource Rate Card'!$N$1:$R$7,5,0),IF(I7="PHP",VLOOKUP(H7,'Resource Rate Card'!$N$1:$R$7,4,0),IF(I7="UK",VLOOKUP(H7,'Resource Rate Card'!$N$1:$R$7,3,0),IF(I7="US",VLOOKUP(H7,'Resource Rate Card'!$N$1:$R$7,2,0)))))) -> 5716.2812 | L7: 1 | M7: 1 | N7: 0 | O7: 0 | P7: 0 | Q7: 0 | R7: 0 | S7: 0 | T7: 0 | U7: 0 | V7: 0 | W7: 0 | X7: =(K7*L7)+(K7*M7)+(K7*N7)+(K7*O7)+(K7*P7)+(K7*Q7)+(K7*R7)+(K7*S7)+(K7*T7)+(K7*U7)+(K7*V7)+(K7*W7) -> 11432.562
A8: =J8&I8&G8 -> QA LeadIndiaC2 | B8: HUM0001 | C8: Auto Case - Auto | D8: Pragya262685 | E8: Pragya Sood | F8: Employee | G8: C2 | H8: =LEFT(G8,1) -> C | I8: India | J8: QA Lead | K8: =IF(F8="Contractor",VLOOKUP(H8,'Resource Rate Card'!$N$10:$O$16,2,0),IF(I8="India",VLOOKUP(H8,'Resource Rate Card'!$N$1:$R$7,5,0),IF(I8="PHP",VLOOKUP(H8,'Resource Rate Card'!$N$1:$R$7,4,0),IF(I8="UK",VLOOKUP(H8,'Resource Rate Card'!$N$1:$R$7,3,0),IF(I8="US",VLOOKUP(H8,'Resource Rate Card'!$N$1:$R$7,2,0)))))) -> 5716.2812 | L8: 1 | M8: 1 | N8: 0 | O8: 0 | P8: 0 | Q8: 0 | R8: 0 | S8: 0 | T8: 0 | U8: 0 | V8: 0 | W8: 0 | X8: =(K8*L8)+(K8*M8)+(K8*N8)+(K8*O8)+(K8*P8)+(K8*Q8)+(K8*R8)+(K8*S8)+(K8*T8)+(K8*U8)+(K8*V8)+(K8*W8) -> 11432.562
A9: =J9&I9&G9 -> Google Tech LeadIndiaC1 | B9: HUM0001 | C9: Auto Case - Auto | D9: Vipasha194680 | E9: Vipasha . | F9: Employee | G9: C1 | H9: =LEFT(G9,1) -> C | I9: India | J9: Google Tech Lead | K9: =IF(F9="Contractor",VLOOKUP(H9,'Resource Rate Card'!$N$10:$O$16,2,0),IF(I9="India",VLOOKUP(H9,'Resource Rate Card'!$N$1:$R$7,5,0),IF(I9="PHP",VLOOKUP(H9,'Resource Rate Card'!$N$1:$R$7,4,0),IF(I9="UK",VLOOKUP(H9,'Resource Rate Card'!$N$1:$R$7,3,0),IF(I9="US",VLOOKUP(H9,'Resource Rate Card'!$N$1:$R$7,2,0)))))) -> 5716.2812 | L9: 1 | M9: 1 | N9: 0 | O9: 0 | P9: 0 | Q9: 0 | R9: 0 | S9: 0 | T9: 0 | U9: 0 | V9: 0 | W9: 0 | X9: =(K9*L9)+(K9*M9)+(K9*N9)+(K9*O9)+(K9*P9)+(K9*Q9)+(K9*R9)+(K9*S9)+(K9*T9)+(K9*U9)+(K9*V9)+(K9*W9) -> 11432.562
A10: =J10&I10&G10 -> Project ManagerPHPD1 | B10: HUM0002 | C10: Auto Case - Pharma D | D10: Anne219593 | E10: Anne Rodelene Pelario Tigol | F10: Employee | G10: D1 | H10: =LEFT(G10,1) -> D | I10: PHP | J10: Project Manager | K10: =IF(F10="Contractor",VLOOKUP(H10,'Resource Rate Card'!$N$10:$O$16,2,0),IF(I10="India",VLOOKUP(H10,'Resource Rate Card'!$N$1:$R$7,5,0),IF(I10="PHP",VLOOKUP(H10,'Resource Rate Card'!$N$1:$R$7,4,0),IF(I10="UK",VLOOKUP(H10,'Resource Rate Card'!$N$1:$R$7,3,0),IF(I10="US",VLOOKUP(H10,'Resource Rate Card'!$N$1:$R$7,2,0)))))) -> 16292.776 | L10: 1 | M10: 1 | N10: 0 | O10: 0 | P10: 0 | Q10: 0 | R10: 0 | S10: 0 | T10: 0 | U10: 0 | V10: 0 | W10: 0 | X10: =(K10*L10)+(K10*M10)+(K10*N10)+(K10*O10)+(K10*P10)+(K10*Q10)+(K10*R10)+(K10*S10)+(K10*T10)+(K10*U10)+(K10*V10)+(K10*W10) -> 32585.552
A11: =J11&I11&G11 -> Google Tech LeadIndiaC2 | B11: HUM0002 | C11: Auto Case - Pharma D | D11: Rajeev235383 | E11: Rajeev Kumar | F11: Employee | G11: C2 | H11: =LEFT(G11,1) -> C | I11: India | J11: Google Tech Lead | K11: =IF(F11="Contractor",VLOOKUP(H11,'Resource Rate Card'!$N$10:$O$16,2,0),IF(I11="India",VLOOKUP(H11,'Resource Rate Card'!$N$1:$R$7,5,0),IF(I11="PHP",VLOOKUP(H11,'Resource Rate Card'!$N$1:$R$7,4,0),IF(I11="UK",VLOOKUP(H11,'Resource Rate Card'!$N$1:$R$7,3,0),IF(I11="US",VLOOKUP(H11,'Resource Rate Card'!$N$1:$R$7,2,0)))))) -> 5716.2812 | L11: 1 | M11: 1 | N11: 0 | O11: 0 | P11: 0 | Q11: 0 | R11: 0 | S11: 0 | T11: 0 | U11: 0 | V11: 0 | W11: 0 | X11: =(K11*L11)+(K11*M11)+(K11*N11)+(K11*O11)+(K11*P11)+(K11*Q11)+(K11*R11)+(K11*S11)+(K11*T11)+(K11*U11)+(K11*V11)+(K11*W11) -> 11432.562
A12: =J12&I12&G12 -> Business AnalystIndiaC2 | B12: HUM0001 | C12: Auto Case - Auto | D12: More186546 | E12: Rohit Vasant More | F12: Employee | G12: C2 | H12: =LEFT(G12,1) -> C | I12: India | J12: Business Analyst | K12: =IF(F12="Contractor",VLOOKUP(H12,'Resource Rate Card'!$N$10:$O$16,2,0),IF(I12="India",VLOOKUP(H12,'Resource Rate Card'!$N$1:$R$7,5,0),IF(I12="PHP",VLOOKUP(H12,'Resource Rate Card'!$N$1:$R$7,4,0),IF(I12="UK",VLOOKUP(H12,'Resource Rate Card'!$N$1:$R$7,3,0),IF(I12="US",VLOOKUP(H12,'Resource Rate Card'!$N$1:$R$7,2,0)))))) -> 5716.2812 | L12: 1 | M12: 1 | N12: 0 | O12: 0 | P12: 0 | Q12: 0 | R12: 0 | S12: 0 | T12: 0 | U12: 0 | V12: 0 | W12: 0 | X12: =(K12*L12)+(K12*M12)+(K12*N12)+(K12*O12)+(K12*P12)+(K12*Q12)+(K12*R12)+(K12*S12)+(K12*T12)+(K12*U12)+(K12*V12)+(K12*W12) -> 11432.562
A13: =J13&I13&G13 -> Google Delivery LeadIndiaD1 | B13: HUM0001 | C13: Auto Case - Auto | D13: Salabh264271 | E13: Salabh Ankur | F13: Employee | G13: D1 | H13: =LEFT(G13,1) -> D | I13: India | J13: Google Delivery Lead | K13: =IF(F13="Contractor",VLOOKUP(H13,'Resource Rate Card'!$N$10:$O$16,2,0),IF(I13="India",VLOOKUP(H13,'Resource Rate Card'!$N$1:$R$7,5,0),IF(I13="PHP",VLOOKUP(H13,'Resource Rate Card'!$N$1:$R$7,4,0),IF(I13="UK",VLOOKUP(H13,'Resource Rate Card'!$N$1:$R$7,3,0),IF(I13="US",VLOOKUP(H13,'Resource Rate Card'!$N$1:$R$7,2,0)))))) -> 10852.348 | L13: 1 | M13: 1 | N13: 0 | O13: 0 | P13: 0 | Q13: 0 | R13: 0 | S13: 0 | T13: 0 | U13: 0 | V13: 0 | W13: 0 | X13: =(K13*L13)+(K13*M13)+(K13*N13)+(K13*O13)+(K13*P13)+(K13*Q13)+(K13*R13)+(K13*S13)+(K13*T13)+(K13*U13)+(K13*V13)+(K13*W13) -> 21704.696
A14: =J14&I14&G14 -> Google DeveloperIndiaB2 | B14: HUM0001 | C14: Auto Case - Auto | D14: Saurav240679 | E14: Saurav Jawahar Rajwani | F14: Employee | G14: B2 | H14: =LEFT(G14,1) -> B | I14: India | J14: Google Developer | K14: =IF(F14="Contractor",VLOOKUP(H14,'Resource Rate Card'!$N$10:$O$16,2,0),IF(I14="India",VLOOKUP(H14,'Resource Rate Card'!$N$1:$R$7,5,0),IF(I14="PHP",VLOOKUP(H14,'Resource Rate Card'!$N$1:$R$7,4,0),IF(I14="UK",VLOOKUP(H14,'Resource Rate Card'!$N$1:$R$7,3,0),IF(I14="US",VLOOKUP(H14,'Resource Rate Card'!$N$1:$R$7,2,0)))))) -> 3151.7248 | L14: 1 | M14: 1 | N14: 0 | O14: 0 | P14: 0 | Q14: 0 | R14: 0 | S14: 0 | T14: 0 | U14: 0 | V14: 0 | W14: 0 | X14: =(K14*L14)+(K14*M14)+(K14*N14)+(K14*O14)+(K14*P14)+(K14*Q14)+(K14*R14)+(K14*S14)+(K14*T14)+(K14*U14)+(K14*V14)+(K14*W14) -> 6303.4495
A15: =J15&I15&G15 -> Google DeveloperIndiaB1 | B15: HUM0002 | C15: Auto Case - Pharma D | D15: Uddeshya220811 | E15: Uddeshya Srivastava | F15: Employee | G15: B1 | H15: =LEFT(G15,1) -> B | I15: India | J15: Google Developer | K15: =IF(F15="Contractor",VLOOKUP(H15,'Resource Rate Card'!$N$10:$O$16,2,0),IF(I15="India",VLOOKUP(H15,'Resource Rate Card'!$N$1:$R$7,5,0),IF(I15="PHP",VLOOKUP(H15,'Resource Rate Card'!$N$1:$R$7,4,0),IF(I15="UK",VLOOKUP(H15,'Resource Rate Card'!$N$1:$R$7,3,0),IF(I15="US",VLOOKUP(H15,'Resource Rate Card'!$N$1:$R$7,2,0)))))) -> 3151.7248 | L15: 1 | M15: 1 | N15: 0 | O15: 0 | P15: 0 | Q15: 0 | R15: 0 | S15: 0 | T15: 0 | U15: 0 | V15: 0 | W15: 0 | X15: =(K15*L15)+(K15*M15)+(K15*N15)+(K15*O15)+(K15*P15)+(K15*Q15)+(K15*R15)+(K15*S15)+(K15*T15)+(K15*U15)+(K15*V15)+(K15*W15) -> 6303.4495
A16: =J16&I16&G16 -> Google DeveloperIndiaB1 | B16: HUM0002 | C16: Auto Case - Pharma D | D16: Koushik264032 | E16: Koushik C S | F16: Employee | G16: B1 | H16: =LEFT(G16,1) -> B | I16: India | J16: Google Developer | K16: =IF(F16="Contractor",VLOOKUP(H16,'Resource Rate Card'!$N$10:$O$16,2,0),IF(I16="India",VLOOKUP(H16,'Resource Rate Card'!$N$1:$R$7,5,0),IF(I16="PHP",VLOOKUP(H16,'Resource Rate Card'!$N$1:$R$7,4,0),IF(I16="UK",VLOOKUP(H16,'Resource Rate Card'!$N$1:$R$7,3,0),IF(I16="US",VLOOKUP(H16,'Resource Rate Card'!$N$1:$R$7,2,0)))))) -> 3151.7248 | L16: 1 | M16: 1 | N16: 0 | O16: 0 | P16: 0 | Q16: 0 | R16: 0 | S16: 0 | T16: 0 | U16: 0 | V16: 0 | W16: 0 | X16: =(K16*L16)+(K16*M16)+(K16*N16)+(K16*O16)+(K16*P16)+(K16*Q16)+(K16*R16)+(K16*S16)+(K16*T16)+(K16*U16)+(K16*V16)+(K16*W16) -> 6303.4495
A17: =J17&I17&G17 -> Data AnalystIndiaB1 | B17: HUM0001 | C17: Auto Case - Auto | D17: Aishani262988 | E17: Aishani Bhatnagar | F17: Employee | G17: B1 | H17: =LEFT(G17,1) -> B | I17: India | J17: Data Analyst | K17: =IF(F17="Contractor",VLOOKUP(H17,'Resource Rate Card'!$N$10:$O$16,2,0),IF(I17="India",VLOOKUP(H17,'Resource Rate Card'!$N$1:$R$7,5,0),IF(I17="PHP",VLOOKUP(H17,'Resource Rate Card'!$N$1:$R$7,4,0),IF(I17="UK",VLOOKUP(H17,'Resource Rate Card'!$N$1:$R$7,3,0),IF(I17="US",VLOOKUP(H17,'Resource Rate Card'!$N$1:$R$7,2,0)))))) -> 3151.7248 | L17: 1 | M17: 1 | N17: 0 | O17: 0 | P17: 0 | Q17: 0 | R17: 0 | S17: 0 | T17: 0 | U17: 0 | V17: 0 | W17: 0 | X17: =(K17*L17)+(K17*M17)+(K17*N17)+(K17*O17)+(K17*P17)+(K17*Q17)+(K17*R17)+(K17*S17)+(K17*T17)+(K17*U17)+(K17*V17)+(K17*W17) -> 6303.4495
... A37: =J37&I37&G37 -> Google DeveloperUSB1 | B37: HUM0001 | C37: Auto Case - Auto | D37: kt_pradeepb | E37: Pradeep Batchu | F37: Employee | G37: B1 | H37: =LEFT(G37,1) -> B | I37: US | J37: Google Developer | K37: =IF(F37="Contractor",VLOOKUP(H37,'Resource Rate Card'!$N$10:$O$16,2,0),IF(I37="India",VLOOKUP(H37,'Resource Rate Card'!$N$1:$R$7,5,0),IF(I37="PHP",VLOOKUP(H37,'Resource Rate Card'!$N$1:$R$7,4,0),IF(I37="UK",VLOOKUP(H37,'Resource Rate Card'!$N$1:$R$7,3,0),IF(I37="US",VLOOKUP(H37,'Resource Rate Card'!$N$1:$R$7,2,0)))))) -> 15690.09 | L37: 1 | M37: 1 | N37: 0 | O37: 0 | P37: 0 | Q37: 0 | R37: 0 | S37: 0 | T37: 0 | U37: 0 | V37: 0 | W37: 0 | X37: =(K37*L37)+(K37*M37)+(K37*N37)+(K37*O37)+(K37*P37)+(K37*Q37)+(K37*R37)+(K37*S37)+(K37*T37)+(K37*U37)+(K37*V37)+(K37*W37) -> 31380.18
A38: =J38&I38&G38 -> Project ManagerIndiaD1 | B38: HUM0001 | C38: Auto Case - Auto | D38: 19030 | E38: Mitali Tripathi | F38: Employee | G38: D1 | H38: =LEFT(G38,1) -> D | I38: India | J38: Project Manager | K38: =IF(F38="Contractor",VLOOKUP(H38,'Resource Rate Card'!$N$10:$O$16,2,0),IF(I38="India",VLOOKUP(H38,'Resource Rate Card'!$N$1:$R$7,5,0),IF(I38="PHP",VLOOKUP(H38,'Resource Rate Card'!$N$1:$R$7,4,0),IF(I38="UK",VLOOKUP(H38,'Resource Rate Card'!$N$1:$R$7,3,0),IF(I38="US",VLOOKUP(H38,'Resource Rate Card'!$N$1:$R$7,2,0)))))) -> 10852.348 | L38: 1 | M38: 1 | N38: 0 | O38: 0 | P38: 0 | Q38: 0 | R38: 0 | S38: 0 | T38: 0 | U38: 0 | V38: 0 | W38: 0 | X38: =(K38*L38)+(K38*M38)+(K38*N38)+(K38*O38)+(K38*P38)+(K38*Q38)+(K38*R38)+(K38*S38)+(K38*T38)+(K38*U38)+(K38*V38)+(K38*W38) -> 21704.696
A39: =J39&I39&G39 -> Project ManagerIndiaC1 | B39: HUM0001 | C39: Auto Case - Auto | D39: 19031 | E39: Harshil Andugulapati | F39: Employee | G39: C1 | H39: =LEFT(G39,1) -> C | I39: India | J39: Project Manager | K39: =IF(F39="Contractor",VLOOKUP(H39,'Resource Rate Card'!$N$10:$O$16,2,0),IF(I39="India",VLOOKUP(H39,'Resource Rate Card'!$N$1:$R$7,5,0),IF(I39="PHP",VLOOKUP(H39,'Resource Rate Card'!$N$1:$R$7,4,0),IF(I39="UK",VLOOKUP(H39,'Resource Rate Card'!$N$1:$R$7,3,0),IF(I39="US",VLOOKUP(H39,'Resource Rate Card'!$N$1:$R$7,2,0)))))) -> 5716.2812 | L39: 1 | M39: 1 | N39: 0 | O39: 0 | P39: 0 | Q39: 0 | R39: 0 | S39: 0 | T39: 0 | U39: 0 | V39: 0 | W39: 0 | X39: =(K39*L39)+(K39*M39)+(K39*N39)+(K39*O39)+(K39*P39)+(K39*Q39)+(K39*R39)+(K39*S39)+(K39*T39)+(K39*U39)+(K39*V39)+(K39*W39) -> 11432.562
A40: =J40&I40&G40 -> Google Delivery LeadIndiaD1 | B40: HUM0002 | C40: Auto Case - Pharma D | D40: 19032 | E40: Ravi Khurana | F40: Employee | G40: D1 | H40: =LEFT(G40,1) -> D | I40: India | J40: Google Delivery Lead | K40: =IF(F40="Contractor",VLOOKUP(H40,'Resource Rate Card'!$N$10:$O$16,2,0),IF(I40="India",VLOOKUP(H40,'Resource Rate Card'!$N$1:$R$7,5,0),IF(I40="PHP",VLOOKUP(H40,'Resource Rate Card'!$N$1:$R$7,4,0),IF(I40="UK",VLOOKUP(H40,'Resource Rate Card'!$N$1:$R$7,3,0),IF(I40="US",VLOOKUP(H40,'Resource Rate Card'!$N$1:$R$7,2,0)))))) -> 10852.348 | L40: 1 | M40: 1 | N40: 0 | O40: 0 | P40: 0 | Q40: 0 | R40: 0 | S40: 0 | T40: 0 | U40: 0 | V40: 0 | W40: 0 | X40: =(K40*L40)+(K40*M40)+(K40*N40)+(K40*O40)+(K40*P40)+(K40*Q40)+(K40*R40)+(K40*S40)+(K40*T40)+(K40*U40)+(K40*V40)+(K40*W40) -> 21704.696
A41: =J41&I41&G41 -> BI Dashboard LeadIndiaD1 | B41: HUM0002 | C41: Auto Case - Pharma D | D41: 19033 | E41: Divya Chaudhary | F41: Employee | G41: D1 | H41: =LEFT(G41,1) -> D | I41: India | J41: BI Dashboard Lead | K41: =IF(F41="Contractor",VLOOKUP(H41,'Resource Rate Card'!$N$10:$O$16,2,0),IF(I41="India",VLOOKUP(H41,'Resource Rate Card'!$N$1:$R$7,5,0),IF(I41="PHP",VLOOKUP(H41,'Resource Rate Card'!$N$1:$R$7,4,0),IF(I41="UK",VLOOKUP(H41,'Resource Rate Card'!$N$1:$R$7,3,0),IF(I41="US",VLOOKUP(H41,'Resource Rate Card'!$N$1:$R$7,2,0)))))) -> 10852.348 | L41: 1 | M41: 1 | N41: 0 | O41: 0 | P41: 0 | Q41: 0 | R41: 0 | S41: 0 | T41: 0 | U41: 0 | V41: 0 | W41: 0 | X41: =(K41*L41)+(K41*M41)+(K41*N41)+(K41*O41)+(K41*P41)+(K41*Q41)+(K41*R41)+(K41*S41)+(K41*T41)+(K41*U41)+(K41*V41)+(K41*W41) -> 21704.696
A42: =J42&I42&G42 -> ETL DeveloperIndiaC1 | B42: HUM0001 | C42: Auto Case - Auto | D42: re_nihals | E42: Nihal Shaik | F42: Employee | G42: C1 | H42: =LEFT(G42,1) -> C | I42: India | J42: ETL Developer | K42: =IF(F42="Contractor",VLOOKUP(H42,'Resource Rate Card'!$N$10:$O$16,2,0),IF(I42="India",VLOOKUP(H42,'Resource Rate Card'!$N$1:$R$7,5,0),IF(I42="PHP",VLOOKUP(H42,'Resource Rate Card'!$N$1:$R$7,4,0),IF(I42="UK",VLOOKUP(H42,'Resource Rate Card'!$N$1:$R$7,3,0),IF(I42="US",VLOOKUP(H42,'Resource Rate Card'!$N$1:$R$7,2,0)))))) -> 5716.2812 | L42: 1 | M42: 1 | N42: 0 | O42: 0 | P42: 0 | Q42: 0 | R42: 0 | S42: 0 | T42: 0 | U42: 0 | V42: 0 | W42: 0 | X42: =(K42*L42)+(K42*M42)+(K42*N42)+(K42*O42)+(K42*P42)+(K42*Q42)+(K42*R42)+(K42*S42)+(K42*T42)+(K42*U42)+(K42*V42)+(K42*W42) -> 11432.562
A43: =J43&I43&G43 -> BI Dashboard UI DeveloperIndiaC1 | B43: HUM0001 | C43: Auto Case - Auto | D43: re_pranjalg | E43: Pranjal Gupta | F43: Employee | G43: C1 | H43: =LEFT(G43,1) -> C | I43: India | J43: BI Dashboard UI Developer | K43: =IF(F43="Contractor",VLOOKUP(H43,'Resource Rate Card'!$N$10:$O$16,2,0),IF(I43="India",VLOOKUP(H43,'Resource Rate Card'!$N$1:$R$7,5,0),IF(I43="PHP",VLOOKUP(H43,'Resource Rate Card'!$N$1:$R$7,4,0),IF(I43="UK",VLOOKUP(H43,'Resource Rate Card'!$N$1:$R$7,3,0),IF(I43="US",VLOOKUP(H43,'Resource Rate Card'!$N$1:$R$7,2,0)))))) -> 5716.2812 | L43: 1 | M43: 1 | N43: 0 | O43: 0 | P43: 0 | Q43: 0 | R43: 0 | S43: 0 | T43: 0 | U43: 0 | V43: 0 | W43: 0 | X43: =(K43*L43)+(K43*M43)+(K43*N43)+(K43*O43)+(K43*P43)+(K43*Q43)+(K43*R43)+(K43*S43)+(K43*T43)+(K43*U43)+(K43*V43)+(K43*W43) -> 11432.562
A44: =J44&I44&G44 -> CX Design LeadUSD1 | B44: HUM0001 | C44: Auto Case - Auto | D44: Natalia203158 | E44: Natalia Militsa | F44: Employee | G44: D1 | H44: =LEFT(G44,1) -> D | I44: US | J44: CX Design Lead | K44: =IF(F44="Contractor",VLOOKUP(H44,'Resource Rate Card'!$N$10:$O$16,2,0),IF(I44="India",VLOOKUP(H44,'Resource Rate Card'!$N$1:$R$7,5,0),IF(I44="PHP",VLOOKUP(H44,'Resource Rate Card'!$N$1:$R$7,4,0),IF(I44="UK",VLOOKUP(H44,'Resource Rate Card'!$N$1:$R$7,3,0),IF(I44="US",VLOOKUP(H44,'Resource Rate Card'!$N$1:$R$7,2,0)))))) -> 34733.886 | L44: 1 | M44: 1 | N44: 0 | O44: 0 | P44: 0 | Q44: 0 | R44: 0 | S44: 0 | T44: 0 | U44: 0 | V44: 0 | W44: 0 | X44: =(K44*L44)+(K44*M44)+(K44*N44)+(K44*O44)+(K44*P44)+(K44*Q44)+(K44*R44)+(K44*S44)+(K44*T44)+(K44*U44)+(K44*V44)+(K44*W44) -> 69467.772
A45: =J45&I45&G45 -> Overall Program LeadPHPE1 | B45: HUM0002 | C45: Auto Case - Pharma D | D45: Mayur16520 | E45: Mayur Shingavi | F45: Employee | G45: E1 | H45: =LEFT(G45,1) -> E | I45: PHP | J45: Overall Program Lead | K45: =IF(F45="Contractor",VLOOKUP(H45,'Resource Rate Card'!$N$10:$O$16,2,0),IF(I45="India",VLOOKUP(H45,'Resource Rate Card'!$N$1:$R$7,5,0),IF(I45="PHP",VLOOKUP(H45,'Resource Rate Card'!$N$1:$R$7,4,0),IF(I45="UK",VLOOKUP(H45,'Resource Rate Card'!$N$1:$R$7,3,0),IF(I45="US",VLOOKUP(H45,'Resource Rate Card'!$N$1:$R$7,2,0)))))) -> 21954.903 | L45: 1 | M45: 1 | N45: 0 | O45: 0 | P45: 0 | Q45: 0 | R45: 0 | S45: 0 | T45: 0 | U45: 0 | V45: 0 | W45: 0 | X45: =(K45*L45)+(K45*M45)+(K45*N45)+(K45*O45)+(K45*P45)+(K45*Q45)+(K45*R45)+(K45*S45)+(K45*T45)+(K45*U45)+(K45*V45)+(K45*W45) -> 43909.806
A46: =J46&I46&G46 -> Engagement LeadUSE1 | B46: HUM0002 | C46: Auto Case - Pharma D | D46: Ankush134427 | E46: Ankush Hora | F46: Employee | G46: E1 | H46: =LEFT(G46,1) -> E | I46: US | J46: Engagement Lead | K46: =IF(F46="Contractor",VLOOKUP(H46,'Resource Rate Card'!$N$10:$O$16,2,0),IF(I46="India",VLOOKUP(H46,'Resource Rate Card'!$N$1:$R$7,5,0),IF(I46="PHP",VLOOKUP(H46,'Resource Rate Card'!$N$1:$R$7,4,0),IF(I46="UK",VLOOKUP(H46,'Resource Rate Card'!$N$1:$R$7,3,0),IF(I46="US",VLOOKUP(H46,'Resource Rate Card'!$N$1:$R$7,2,0)))))) -> 38837.379 | L46: 1 | M46: 1 | N46: 0 | O46: 0 | P46: 0 | Q46: 0 | R46: 0 | S46: 0 | T46: 0 | U46: 0 | V46: 0 | W46: 0 | X46: =(K46*L46)+(K46*M46)+(K46*N46)+(K46*O46)+(K46*P46)+(K46*Q46)+(K46*R46)+(K46*S46)+(K46*T46)+(K46*U46)+(K46*V46)+(K46*W46) -> 77674.758

Sheet Project Burn Summary
A1: Project Code | B1: Project Name | C1: Month | D1: Monthly Cost | E1: Cumulative Project Cost | F1: Remaining Budget | G1: RAG Status | H1: Revenue Till Date | I1: Gross Margin | J1: Gross Margin%
A2: HUM0001 | B2: Auto Case - Auto | C2: 46048 | D2: =SUMIFS('Monthly Resource Allocation'!X:X,'Monthly Resource Allocation'!B:B,'Project Burn Summary'!A2) -> 459717.12 | E2: =SUMIF(A:A,A2,D:D) -> 459717.12 | F2: =VLOOKUP(A2,'Project Master'!A:E,5,)-E2 -> 9540282.9 | G2: =IFERROR(IF(E2/VLOOKUP(A2,'Project Master'!A:E,5,0)<0.7,"Green",IF(E2/VLOOKUP(A2,'Project Master'!A:E,5,0)<0.9,"Amber","Red")),"") -> Green | H2: =VLOOKUP(A2,'Project Master'!A:G,7,0)*(E2/VLOOKUP(A2,'Project Master'!A:G,5,0)) -> 597632.25 | I2: =H2-E2 -> 137915.14 | J2: =IFERROR(I2/H2,0) -> 0.23076923
A3: HUM0002 | B3: Auto Case - Pharma D | C3: 46048 | D3: =SUMIFS('Monthly Resource Allocation'!X:X,'Monthly Resource Allocation'!B:B,'Project Burn Summary'!A3) -> 378413.29 | E3: =SUMIF(A:A,A3,D:D) -> 378413.29 | F3: =VLOOKUP(A3,'Project Master'!A:E,5,)-E3 -> 7121586.7 | G3: =IFERROR(IF(E3/VLOOKUP(A3,'Project Master'!A:E,5,0)<0.7,"Green",IF(E3/VLOOKUP(A3,'Project Master'!A:E,5,0)<0.9,"Amber","Red")),"") -> Green | H3: =VLOOKUP(A3,'Project Master'!A:G,7,0)*(E3/VLOOKUP(A3,'Project Master'!A:G,5,0)) -> 479323.49 | I3: =H3-E3 -> 100910.21 | J3: =IFERROR(I3/H3,0) -> 0.21052632

Sheet MoM Resource Utilisation
A1: Project Code | B1: Project Name | C1: Emp Code | D1: Emp Name | E1: Role | F1: Month | G1: Allocation% | H1: Utilisation Status
A2: HUM0001 | B2: Auto Case - Auto | C2: Abhishek191376 | D2: Abhishek Ganguly
A3: HUM0001 | B3: Auto Case - Auto | C3: Amit127844 | D3: Amit Jha
A4: HUM0001 | B4: Auto Case - Auto | C4: Ananya193970 | D4: Ananya Borah
A5: HUM0002 | B5: Auto Case - Pharma D | C5: 10125 | D5: Krishna .
A6: HUM0002 | B6: Auto Case - Pharma D | C6: Madhurima217704 | D6: Madhurima Boral
A7: HUM0001 | B7: Auto Case - Auto | C7: Piyush231958 | D7: Piyush Lahiry
A8: HUM0001 | B8: Auto Case - Auto | C8: Pragya262685 | D8: Pragya Sood
A9: HUM0001 | B9: Auto Case - Auto | C9: Vipasha194680 | D9: Vipasha .
A10: HUM0002 | B10: Auto Case - Pharma D | C10: Anne219593 | D10: Anne Rodelene Pelario Tigol
A11: HUM0002 | B11: Auto Case - Pharma D | C11: Rajeev235383 | D11: Rajeev Kumar
A12: HUM0001 | B12: Auto Case - Auto | C12: More186546 | D12: Rohit Vasant More
A13: HUM0001 | B13: Auto Case - Auto | C13: Salabh264271 | D13: Salabh Ankur
A14: HUM0001 | B14: Auto Case - Auto | C14: Saurav240679 | D14: Saurav Jawahar Rajwani
A15: HUM0002 | B15: Auto Case - Pharma D | C15: Uddeshya220811 | D15: Uddeshya Srivastava
A16: HUM0002 | B16: Auto Case - Pharma D | C16: Koushik264032 | D16: Koushik C S
A17: HUM0001 | B17: Auto Case - Auto | C17: Aishani262988 | D17: Aishani Bhatnagar
... A37: HUM0001 | B37: Auto Case - Auto | C37: kt_pradeepb | D37: Pradeep Batchu
A38: HUM0001 | B38: Auto Case - Auto | C38: 19030 | D38: Mitali Tripathi
A39: HUM0001 | B39: Auto Case - Auto | C39: 19031 | D39: Harshil Andugulapati
A40: HUM0002 | B40: Auto Case - Pharma D | C40: 19032 | D40: Ravi Khurana
A41: HUM0002 | B41: Auto Case - Pharma D | C41: 19033 | D41: Divya Chaudhary
A42: HUM0001 | B42: Auto Case - Auto | C42: re_nihals | D42: Nihal Shaik
A43: HUM0001 | B43: Auto Case - Auto | C43: re_pranjalg | D43: Pranjal Gupta
A44: HUM0001 | B44: Auto Case - Auto | C44: Natalia203158 | D44: Natalia Militsa
A45: HUM0002 | B45: Auto Case - Pharma D | C45: Mayur16520 | D45: Mayur Shingavi
A46: HUM0002 | B46: Auto Case - Pharma D | C46: Ankush134427 | D46: Ankush Hora

Sheet Resource Allocation Till Date
A1: Project Code | B1: Project Name | C1: Emp Code | D1: Emp Name | E1: Role | F1: Total Allocation% | G1: Months Count | H1: Avg Utilisation% | I1: Utilisation Status

Sheet Project Timeline Burn  (2)
A1: Project Name | B1: Project Name | C1: Period (Monthly) | D1: Total Cost | E1: Actual Revenue | F1: Revenue Realised | G1: Burn Rate | H1: Gross Margin | I1: Burn Status
A2: HUM0001 | B2: Auto Case - Auto | C2: 46048 | D2: =SUMIFS('Monthly Resource Allocation'!X:X,'Monthly Resource Allocation'!B:B,'Project Timeline Burn (2)'!A2) -> 459717.12 | E2: =SUMIFS('Project Wise Revenue'!E:E,'Project Wise Revenue'!B:B,'Project Timeline Burn (2)'!B2,'Project Wise Revenue'!C:C,'Project Timeline Burn (2)'!C2) -> 200000 | F2: =E2/SUMIFS('Project Wise Revenue'!E:E,'Project Wise Revenue'!B:B,'Project Timeline Burn (2)'!B2,'Project Wise Revenue'!C:C,'Project Timeline Burn (2)'!C2) -> 1 | G2: =D2/E2 -> 2.2985856 | H2: =(E2-D2)/E2 -> -1.2985856 | I2: =IF(G2>0.85,"Red",IF(G2>0.6,"Amber","Green")) -> Red
A3: HUM0002 | B3: Auto Case - Pharma D | C3: 46079 | D3: =SUMIFS('Monthly Resource Allocation'!X:X,'Monthly Resource Allocation'!B:B,'Project Timeline Burn (2)'!A3) -> 378413.29 | E3: =SUMIFS('Project Wise Revenue'!E:E,'Project Wise Revenue'!B:B,'Project Timeline Burn (2)'!B3) -> 450000 | F3: =E3/SUMIFS('Project Wise Revenue'!E:E,'Project Wise Revenue'!B:B,'Project Timeline Burn (2)'!B3) -> 1 | G3: =D3/E3 -> 0.84091841 | H3: =(E3-D3)/E3 -> 0.15908159 | I3: =IF(G3>0.85,"Red",IF(G3>0.75,"Amber","Green")) -> Amber

Sheet Project Wise Summary
A1: Project ID | B1: Project Name | C1: Start Date | D1: End Date | E1: Total Budget | F1: Total Effort | G1: Cost till Date | H1: Project Budget | I1: Budget Burn Down
B2: Auto Case - Auto | F2: =SUMIF('Project Resource Details'!B:B,'Project Wise Summary'!B2,'Project Resource Details'!BM:BM) -> 32 | G2: =SUMIF('Project Resource Details'!B:B,'Project Wise Summary'!B2,'Project Resource Details'!BN:BN) -> 0 | I2: =G2/H2 -> #DIV/0!
B3: Auto Case - Pharma D
B4: Auto Case - PTS
B5: Auto Case - STP
B6: Call Transcription - Auto, PTS, STP
B7: Call Transcription - Pharma D
B8: CCaaS Modernization
B9: Chat Summarization-ProviderSolutions
B10: Chat VA - Pharma D
B11: EAAA - Provider Solutions
B12: EAAA Enhancements - Provider Solutions
B13: Email AAA - MSD
B14: Email AAA - Pharma D
... B31: VirtualAssistant - Customer Centre Portal

Sheet Project Resource Details
I1: WEEKLY LOGGED HOURS
A2: Project ID | B2: Project Name | C2: Resource ID | D2: Resource Name | E2: Resource Type | F2: Resource Status | G2: Weekly Rate | H2: Yearly Rate | I2: Wk01 | J2: Wk02 | K2: Wk03 | L2: Wk04 | M2: Wk05 | N2: Wk06 | O2: Wk07 | P2: Wk08 | Q2: Wk09 | R2: Wk10 | S2: Wk11 | T2: Wk12 | U2: Wk13 | V2: Wk14 | W2: Wk15 | X2: Wk16 | Y2: Wk17 | Z2: Wk18 | AA2: Wk19 | AB2: Wk20 | AC2: Wk21 | AD2: Wk22 | AE2: Wk23 | AF2: Wk24 | AG2: Wk25 | AH2: Wk26 | AI2: Wk27 | AJ2: Wk28 | AK2: Wk29 | AL2: Wk30 | AM2: Wk31 | AN2: Wk32 | AO2: Wk33 | AP2: Wk34 | AQ2: Wk35 | AR2: Wk36 | AS2: Wk37 | AT2: Wk38 | AU2: Wk39 | AV2: Wk40 | AW2: Wk41 | AX2: Wk42 | AY2: Wk43 | AZ2: Wk44 | BA2: Wk45 | BB2: Wk46 | BC2: Wk47 | BD2: Wk48 | BE2: Wk49 | BF2: Wk50 | BG2: Wk51 | BH2: Wk52 | BI2: Wk53 | BJ2: Wk54 | BK2: Wk55 | BL2: Wk56 | BM2: Total hrs logged till date | BN2: Cost till date | BO2: Budget | BP2: Budget Burn Down
B3: Auto Case - Auto | F3: FTE/Contractor | H3: 0 | I3: 8 | J3: 8 | K3: 8 | L3: 8 | BM3: =SUM(I3:BL3) -> 32 | BN3: =H3*BM3 -> 0 | BP3: =BN3/BO3 -> #DIV/0!
A6: Week on week hours have to be plotted against each resource to achieve the total cost
A7: Need to understand the Factors affecting the change in the weekly rate card of the resources if any
A9: Factors affecting the change in the weekly rate of the resources if any
A10: Is total hrs logged by the resources available on weekly basis
A11: Budget of the resources is available at the start of the project and remains the same throughout?
A12: Start date and end date of the project has to be captured to get the months left
A13: Total Effort is the Resource logged hrs in the project resource details
A14: Total Cost is the yearly rate by hrs logged by the resource
A15: Budget is the rate of the project that comes from the SOW

Sheet Project Resource Details (2)
H1: Wk01
A2: Project ID | B2: Project Name | C2: Resource ID | D2: Resource Name | E2: Resource Type | F2: Resource Status | G2: Weekly Rate | H2: Total Hrs Logged | I2: Total Cost | J2: Budget | K2: Budget Burn Down
F3: FTE/Contractor | I3: =G3*H3 -> 0 | J3: 1 | K3: =I3/J3 -> 0

Sheet Resource Wise Summary
A2: Project ID | B2: Project Name | C2: Resource ID | D2: Resource Name | E2: Resource Type | F2: Cost Per Hr. | G2: Total Hrs | H2: Total Cost | I2: Budget | J2: Budget Burn Down | K2: Week
H3: =F3*G3 -> 0 | I3: 1 | J3: =H3/I3 -> 0 | K3: Wk01
K4: Wk02
